skill_audit/__init__.py
skill_audit/cli.py
skill_audit/core/__init__.py
skill_audit/core/aggregator.py
skill_audit/core/output.py
skill_audit/core/scanner.py
skill_audit/core/tools.py
skill_audit/scanners/__init__.py
skill_audit/scanners/prompt.py
skill_audit/scanners/secrets.py
skill_audit/scanners/semgrep.py
skill_audit/scanners/shellcheck.py
skill_audit-0.1.0.dist-info/METADATA
skill_audit-0.1.0.dist-info/WHEEL
skill_audit-0.1.0.dist-info/entry_points.txt
skill_audit-0.1.0.dist-info/RECORD
